MANIFEST.in
setup.py
Ion.egg-info/PKG-INFO
Ion.egg-info/SOURCES.txt
Ion.egg-info/dependency_links.txt
Ion.egg-info/entry_points.txt
Ion.egg-info/requires.txt
Ion.egg-info/top_level.txt
ion/__init__.py
ion/bus.py
ion/cache.py
ion/context.py
ion/controllers.py
ion/db.py
ion/forms.py
ion/fs.py
ion/plugins.py
ion/server.py
ion/services.py
ion/settings.py
ion/sqlalchemy_tool.py
ion/test_helpers.py
ion/console/__init__.py
ion/console/ion_console.py
ion/console/providers.py
ion/console/new_project/src/__init__.py
ion/console/new_project/src/config.ini
ion/console/new_project/src/main/__init__.py
ion/console/new_project/src/main/controllers/__init__.py
ion/console/new_project/src/main/controllers/controllers.py
ion/console/new_project/src/main/media/css/readme.rst
ion/console/new_project/src/main/media/img/readme.rst
ion/console/new_project/src/main/media/js/readme.rst
ion/console/new_project/src/main/models/__init__.py
ion/console/new_project/src/main/templates/__init__.py
ion/console/new_project/src/main/templates/index.html
ion/console/new_project/src/main/tests/__init__.py
ion/console/new_project/src/main/tests/functional/__init__.py
ion/console/new_project/src/main/tests/unit/__init__.py
ion/console/new_project/src/main/tests/unit/test_default_controller.py