Metadata-Version: 1.0
Name: Ion
Version: 0.6.4
Summary: Ion is an MVC Web Framework
Home-page: http://www.ionwebframework.org
Author: Bernardo Heynemann
Author-email: heynemann@gmail.com
License: OSI
Keywords: MVC Web Framework
Platform: UNKNOWN
Classifier: Development Status :: 4 - Beta
Classifier: Intended Audience :: Developers
Classifier: License :: OSI Approved
Classifier: Natural Language :: English
Classifier: Operating System :: MacOS
Classifier: Operating System :: Microsoft :: Windows
Classifier: Operating System :: POSIX :: Linux
Classifier: Programming Language :: Python :: 2.6
